yxapollo/Apollo.py
yxapollo/ApolloClient.py
yxapollo/__init__.py
yxapollo-0.0.7.dist-info/LICENSE
yxapollo-0.0.7.dist-info/METADATA
yxapollo-0.0.7.dist-info/WHEEL
yxapollo-0.0.7.dist-info/top_level.txt
yxapollo-0.0.7.dist-info/RECORD
