Metadata-Version: 2.1
Name: yxapollo
Version: 0.0.7
Summary: python apollo connector
Home-page: https://you.163.com
Author: Yanxuan
Author-email: zhuxulv@corp.netease.com
Classifier: Programming Language :: Python :: 3
Classifier: License :: OSI Approved :: MIT License
Classifier: Operating System :: OS Independent
License-File: LICENSE
